linuxdir2html/__init__.py
linuxdir2html/linuxdir2html.py
linuxdir2html/template.html
linuxdir2html-1.6.1.dist-info/licenses/LICENSE
linuxdir2html-1.6.1.dist-info/METADATA
linuxdir2html-1.6.1.dist-info/WHEEL
linuxdir2html-1.6.1.dist-info/entry_points.txt
linuxdir2html-1.6.1.dist-info/top_level.txt
linuxdir2html-1.6.1.dist-info/RECORD
