Metadata-Version: 2.4
Name: linuxdir2html
Version: 1.6.1
Summary: HTML directory listing
Home-page: https://github.com/homeisfar/LinuxDir2HTML
Author: Ali Homafar
Author-email: home.isfar@gmail.com
Classifier: Programming Language :: Python :: 3
Classifier: Environment :: Console
Classifier: License :: OSI Approved :: GNU General Public License v3 (GPLv3)
Classifier: Operating System :: OS Independent
Requires-Python: >=3.6
License-File: LICENSE
Dynamic: author
Dynamic: author-email
Dynamic: classifier
Dynamic: description
Dynamic: description-content-type
Dynamic: home-page
Dynamic: license-file
Dynamic: requires-python
Dynamic: summary
